MANIFEST.in
README.md
setup.py
MeowApp.egg-info/PKG-INFO
MeowApp.egg-info/SOURCES.txt
MeowApp.egg-info/dependency_links.txt
MeowApp.egg-info/entry_points.txt
MeowApp.egg-info/requires.txt
MeowApp.egg-info/top_level.txt
meow/__init__.py
meow/app.py
meow/config.py
meow/front.py
meow/meow_server.py
meow/config/__init__.py
meow/server/__init__.py
meow/server/handlers/__init__.py
meow/server/handlers/desktop_entries.py
meow/server/handlers/file_serve_handler.py
meow/server/handlers/kill.py
meow/server/handlers/sudo_switch.py
meow/www/3rdpartylicenses.txt
meow/www/fa-brands-400.0d37e867715b74524839.ttf
meow/www/fa-brands-400.6fa7434ed84bcd8a18f2.eot
meow/www/fa-brands-400.a94c97ae7d90c52c411a.woff
meow/www/fa-brands-400.cf8137d345fbab9b2afd.svg
meow/www/fa-brands-400.cfa1eb9401f9dfe70058.woff2
meow/www/fa-light-300.086ab29ed9100a1f6468.woff
meow/www/fa-light-300.133b6087a9cb7a3d34da.woff2
meow/www/fa-light-300.2626ea387360e0ce3203.eot
meow/www/fa-light-300.5708aa3afde9acd9385b.ttf
meow/www/fa-light-300.c1dc37c47455c39f0b04.svg
meow/www/fa-regular-400.49585be028d17da4be7d.eot
meow/www/fa-regular-400.5e0880da30da346a7e09.woff2
meow/www/fa-regular-400.9bb9bf9eaecd702b9a5a.ttf
meow/www/fa-regular-400.b4b44ae7eebc091b4d67.svg
meow/www/fa-regular-400.de636d1a035e6ec6ba33.woff
meow/www/fa-solid-900.52b4305f412173e54afc.woff
meow/www/fa-solid-900.9f25a06f1eae00a44c94.woff2
meow/www/fa-solid-900.c251229a9fe84a992c49.eot
meow/www/fa-solid-900.d7b5dc7420e4d4102c2b.svg
meow/www/fa-solid-900.ef88392f3412b7348fa3.ttf
meow/www/favicon.ico
meow/www/index.html
meow/www/main.2552fb8e1cb8ac7165e5.js
meow/www/polyfills.730f9e1209fa5b8da87d.js
meow/www/runtime.ec2944dd8b20ec099bf3.js
meow/www/styles.8ae9f420fbbb23628819.css
meow/www/assets/LICENSE.txt
meow/www/assets/meow.svg
meow/www/assets/missing.png
meow/www/assets/fonts/Roboto-Black.ttf
meow/www/assets/fonts/Roboto-BlackItalic.ttf
meow/www/assets/fonts/Roboto-Bold.ttf
meow/www/assets/fonts/Roboto-BoldItalic.ttf
meow/www/assets/fonts/Roboto-Italic.ttf
meow/www/assets/fonts/Roboto-Light.ttf
meow/www/assets/fonts/Roboto-LightItalic.ttf
meow/www/assets/fonts/Roboto-Medium.ttf
meow/www/assets/fonts/Roboto-MediumItalic.ttf
